{
  "button": {
    "small": {
      "height": 36,
      "padding": {
        "horizontal": 16,
        "vertical": 8
      },
      "gap": 8
    },
    "medium": {
      "height": 40,
      "padding": {
        "horizontal": 16,
        "vertical": 8
      },
      "gap": 8
    },
    "large": {
      "height": 44,
      "padding": {
        "horizontal": 16,
        "vertical": 8
      },
      "gap": 12
    },
    "borderRadius": 64
  },
  "progressBar": {
    "height": 8,
    "borderRadius": 8
  },
  "inputField": {
    "borderRadius": 8,
    "padding": {
      "horizontal": 16,
      "vertical": 12
    }
  },
  "dropdown": {
    "borderRadius": 12,
    "height": 44,
    "padding": {
      "horizontal": 16,
      "vertical": 12
    },
    "gap": 8,
    "labelFontSize": 12,
    "dropdownMaxHeight": 220,
    "elevation": 4,
    "selectedItemColor": "#0047AB",
    "selectedTextColor": "#FFFFFF"
  },
  "searchBar": {
    "enabled_small": {
      "height": 40,
      "borderRadius": 12,
      "iconSize": 20,
      "paddingHorizontal": 16
    },
    "enabled_large": {
      "height": 44,
      "borderRadius": 16,
      "iconSize": 20,
      "paddingHorizontal": 16
    },
    "hovered_small": {
      "height": 40,
      "borderRadius": 12,
      "iconSize": 20,
      "paddingHorizontal": 16
    },
    "hovered_large": {
      "height": 44,
      "borderRadius": 16,
      "iconSize": 20,
      "paddingHorizontal": 16
    },
    "icons": {
      "search": "assets/icons/search.svg",
      "microphone": "assets/icons/microphone-2.svg"
    }
  }
}